.DS_Store
dtreeplot/.DS_Store
dtreeplot/__init__.py
dtreeplot/plot.py
dtreeplot/js/d3.v6.min.js
dtreeplot/js/plotter.js
dtreeplot-0.1.2.dist-info/LICENSE.txt
dtreeplot-0.1.2.dist-info/METADATA
dtreeplot-0.1.2.dist-info/WHEEL
dtreeplot-0.1.2.dist-info/top_level.txt
dtreeplot-0.1.2.dist-info/RECORD
