Metadata-Version: 2.1
Name: dtreeplot
Version: 0.1.2
Summary: A Decision Tree Visualization Packages.
Home-page: 
Author: suyin
Author-email: suyin1203@gmail.com
Keywords: decision tree Visualize
Classifier: License :: OSI Approved :: MIT License
Classifier: Programming Language :: Python :: 3
Classifier: Programming Language :: Python :: 3.4
Classifier: Programming Language :: Python :: 3.5
Classifier: Programming Language :: Python :: 3.6
Classifier: Programming Language :: Python :: 3.7
Classifier: Programming Language :: Python :: 3.8
Classifier: Programming Language :: Python :: 3.9
License-File: LICENSE.txt
